alu_.sv
module alu_(
    input   logic [31:0]      ALUop1, ALUop2,
    input   logic [2:0]            ALUctrl,
    output  logic [31:0]       ALUout,
    output  logic               EQ

);
always_comb 
    case (ALUctrl)
    3'b000:     ALUout = ALUop1 + ALUop2;
    3'b001:     ALUout = ALUop1 - ALUop2;
    3'b010:     ALUout = ALUop1 & ALUop2;
    3'b011:     ALUout = ALUop1 | ALUop2;
    default:    ALUout = 0;
    endcase
    assign      EQ = ALUop1 == ALUop2 ? 1:0;

endmodule

Reg_file.sv
module Reg_file #(
    parameter ADDRESS_WIDTH = 16,
              DATA_WIDTH = 32
)(
    input   logic [ADDRESS_WIDTH-1:0]        AD1,
    input   logic [ADDRESS_WIDTH-1:0]        AD2,
    input   logic [ADDRESS_WIDTH-1:0]        AD3,
    input   logic                            WE3,
    input   logic [DATA_WIDTH-1:0]           WD3,
    input   logic                            clk,
    output  logic [DATA_WIDTH-1:0]           RD1,
    output  logic [DATA_WIDTH-1:0]           RD2,
    output  logic [DATA_WIDTH-1:0]           a0

);

    logic [DATA_WIDTH-1:0] reg_array [2**ADDRESS_WIDTH-1:0];

    always_ff @ (posedge clk) 
        if (WE3 == 1'b1)
            reg_array[AD3] <= WD3;

    assign a0 = reg_array[{16'b01010}];

    always_ff @ *
    begin
        RD1 = reg_array[AD1];
        RD2 = reg_array[AD2];
    end
        
endmodule

ALU.sv
module ALU #(
    parameter A_WIDTH = 16,
              D_WIDTH = 32  
)(
    // interface signals
    input logic               clk, 
    input logic               ALUsrc, 
    input logic [2:0]         ALUctrl, 
    input logic [31:0]          ImmOp, 
    input logic               WE3,  
    input logic [A_WIDTH-1:0] AD1, 
    input logic [A_WIDTH-1:0] AD2,
    input logic [A_WIDTH-1:0] AD3,
    output logic              EQ,
    output logic [D_WIDTH-1:0] a0
);

    logic [D_WIDTH-1:0] regOp2; 
    logic [D_WIDTH-1:0] ALUop1; 
    logic [D_WIDTH-1:0] ALUop2; 
    logic [D_WIDTH-1:0] ALUout; 

Reg_file regfile(
    .clk (clk),
    .AD1 (AD1),
    .AD2 (AD2),
    .AD3 (AD3),
    .WE3 (WE3),
    .RD1 (ALUop1),
    .RD2 (regOp2),
    .WD3 (ALUout),
    .a0 (a0)
);


  assign ALUop2 = ALUsrc ?  ImmOp : regOp2;


alu_ addralu (
    .ALUop1 (ALUop1),
    .ALUop2 (ALUop2),
    .EQ  (EQ),
    .ALUctrl (ALUctrl),
    .ALUout (ALUout)
);



endmodule

ControlUnit.sv
module ControlUnit #(
    parameter   DATA_WIDTH = 32
)(
    input  logic [DATA_WIDTH-1:0]  instr,
    input  logic                   EQ,
    output logic                   RegWrite,
    output logic [2:0]             ALUctrl,
    output logic                   ALUsrc,
    output logic [DATA_WIDTH-21:0] ImmSrc,
    output logic                   PCsrc
);

logic [6:0] opcode;
logic [2:0] funct3;

assign opcode = instr[6:0];
assign funct3 = instr[14:12];

always_latch @(instr) 
    if (opcode == 7'b0010011 & funct3 == 3'b000) begin
        assign ALUctrl = 3'b000;
        assign ALUsrc = 1'b0;
        assign RegWrite = 1'b1; 
    end else if (opcode==7'b0010011 & funct3==3'b000 & EQ == 0) begin  
        assign ALUctrl = 3'b000;
        assign ALUsrc = 1'b1;
        assign RegWrite = 1'b1;
        assign ImmSrc = instr[31:20];
    end else if (opcode == 7'b1100011 & funct3 == 3'b001 & EQ == 0) begin  //bne
        assign ImmSrc = instr[31:20];
        assign RegWrite = 1'b0;
        if (EQ==0)
        assign  PCsrc = 1'b1;
        else
            assign PCsrc = 1'b0; 
    end

endmodule

PC_Reg.sv
module PC_Reg (
    input logic [31:0]            next_PC,
    input logic                   rst,
    output logic [31:0]           PC
);

always_ff @ (posedge clk, posedge rst)
    if (rst)
        sreg <= 32'b0;
    else 
        sreg <= next_PC;

assign PC = sreg;

endmodule

Countermux.sv
module Countermux (
  input logic [31:0]      PC,       
  input logic [31:0]      ImmOp, 
  input logic             PCsrc,
  output  logic [31:0]    next_PC  
);

logic  [31:0]       branch_PC;  
logic  [31:0]       inc_PC;

assign branch_PC = PC + ImmOp;
assign inc_PC = PC + 32'b100;
assign next_PC = PCsrc ? branch_PC : inc_PC;

endmodule

toppc.sv
module toppc (          
  input logic  [31:0]      ImmOp,
  input logic              rst,   
  input logic              PCsrc,
  input logic              clk,
  output logic  [31:0]     PC
);

  logic  [31:0]        next_PC;    

Countermux Countermux ( 
  .PC (PC),
  .ImmOp (ImmOp),
  .next_PC (next_PC),
  .PCsrc (PCsrc)
);

PC_Reg  PC_Reg( 
  .rst (rst),
  .next_PC (next_PC),
  .PC (PC)
);

endmodule

SignEx.sv
module SignEx (
    input logic [11:0] ImmSrc,
    input logic [31:0] instr,
    output logic [31:0] ImmOp
);

logic [4:0] rd;
logic  [6:0] opcode;
logic [19:0] imm;

assign opcode = instr[6:0];
assign rd = instr[11:7];
assign imm = {{8{ImmSrc[11]}},ImmSrc};

always_latch @(instr) 
    if (opcode == 7'b0010011) begin
        assign ImmOp = {imm,rd,opcode};
    end else if (opcode == 7'b1100011) begin //bne
        assign ImmOp = {ImmSrc[11],ImmSrc[9:4],instr[24:12],ImmSrc[3:0],ImmSrc[10],opcode};
    end 

endmodule

InstrMem.sv
module InstrMem #(
    parameter   ADDRESS_WIDTH = 32,
                DATA_WIDTH = 32
)(
    input  logic  [ADDRESS_WIDTH-1:0]  addr,
    output logic  [DATA_WIDTH-1:0]     instr
);

logic  [7:0] rom_array [2**16-1:0];

initial begin
        $display("Loading rom.");
        $readmemh("Lab4.mem", rom_array);
end;

assign instr = {rom_array [addr+3], rom_array [addr+2], rom_array [addr+1], rom_array[addr+0]};

endmodule

cpu.sv
module cpu #(
    parameter A_WIDTH = 16,
              D_WIDTH = 32
)(
    //interface signals
    input logic clk, 
    input logic rst, 
    output logic [D_WIDTH-1:0]a0
);

    //connecting wires
logic [D_WIDTH-1:0] PC; 
logic [D_WIDTH-1:0] instr; 
logic PCsrc;
logic [2:0]  ALUctrl; 
logic ALUsrc; 
logic EQ; 
logic regwrite; 
logic [11:0] Immsrc; 
logic [31:0] Immop; 
logic [A_WIDTH-1:0] rs1;
logic [A_WIDTH-1:0] rs2;
logic [A_WIDTH-1:0] rd;

assign rs1 = {{11'b0},instr[19:15]};
assign rs2 = {{11'b0},instr[24:20]};
assign rd = {{11'b0},instr[11:7]};

InstrMem memory(
    .addr (PC),
    .instr (instr)
);

SignEx immext(
    .ImmOp (Immop), 
    .ImmSrc (Immsrc),
    .instr(instr)
);

toppc pc (
    .clk (clk), 
    .rst (rst),
    .PC (PC),  
    .PCsrc (PCsrc),
    .ImmOp (Immop)
);

ControlUnit controlunit (
    .PCsrc (PCsrc), 
    .RegWrite (regwrite), 
    .ALUctrl (ALUctrl),
    .ALUsrc (ALUsrc), 
    .ImmSrc (Immsrc), 
    .EQ (EQ), 
    .instr (instr)
);

ALU alublock(
    .AD1 (rs1), 
    .AD2 (rs2), 
    .AD3 (rd),
    .WE3 (regwrite),
    .clk (clk), 
    .EQ (EQ), 
    .ALUctrl (ALUctrl),
    .ALUsrc (ALUsrc),
    .ImmOp (Immop), 
    .a0 (a0)
);

endmodule

cpu.vcd
$version Generated by VerilatedVcd $end
$date Fri Nov 25 00:00:03 2022 $end
$timescale 1ps $end

 $scope module TOP $end
  $var wire 32 6 a0 [31:0] $end
  $var wire  1 4 clk $end
  $var wire  1 5 rst $end
  $scope module cpu $end
   $var wire  3 , ALUctrl [2:0] $end
   $var wire  1 - ALUsrc $end
   $var wire 32 = A_WIDTH [31:0] $end
   $var wire 32 > D_WIDTH [31:0] $end
   $var wire  1 . EQ $end
   $var wire 32 1 Immop [31:0] $end
   $var wire 12 0 Immsrc [11:0] $end
   $var wire 32 7 PC [31:0] $end
   $var wire  1 + PCsrc $end
   $var wire 32 6 a0 [31:0] $end
   $var wire  1 4 clk $end
   $var wire 32 # instr [31:0] $end
   $var wire 16 & rd [15:0] $end
   $var wire  1 / regwrite $end
   $var wire 16 $ rs1 [15:0] $end
   $var wire 16 % rs2 [15:0] $end
   $var wire  1 5 rst $end
   $scope module alublock $end
    $var wire 16 $ AD1 [15:0] $end
    $var wire 16 % AD2 [15:0] $end
    $var wire 16 & AD3 [15:0] $end
    $var wire  3 , ALUctrl [2:0] $end
    $var wire 32 ' ALUop1 [31:0] $end
    $var wire 32 2 ALUop2 [31:0] $end
    $var wire 32 9 ALUout [31:0] $end
    $var wire  1 - ALUsrc $end
    $var wire 32 = A_WIDTH [31:0] $end
    $var wire 32 > D_WIDTH [31:0] $end
    $var wire  1 . EQ $end
    $var wire 32 1 ImmOp [31:0] $end
    $var wire  1 / WE3 $end
    $var wire 32 6 a0 [31:0] $end
    $var wire  1 4 clk $end
    $var wire 32 8 regOp2 [31:0] $end
    $scope module addralu $end
     $var wire  3 , ALUctrl [2:0] $end
     $var wire 32 ' ALUop1 [31:0] $end
     $var wire 32 2 ALUop2 [31:0] $end
     $var wire 32 9 ALUout [31:0] $end
     $var wire  1 . EQ $end
    $upscope $end
    $scope module regfile $end
     $var wire 16 $ AD1 [15:0] $end
     $var wire 16 % AD2 [15:0] $end
     $var wire 16 & AD3 [15:0] $end
     $var wire 32 = ADDRESS_WIDTH [31:0] $end
     $var wire 32 > DATA_WIDTH [31:0] $end
     $var wire 32 ' RD1 [31:0] $end
     $var wire 32 8 RD2 [31:0] $end
     $var wire 32 9 WD3 [31:0] $end
     $var wire  1 / WE3 $end
     $var wire 32 6 a0 [31:0] $end
     $var wire  1 4 clk $end
    $upscope $end
   $upscope $end
   $scope module controlunit $end
    $var wire  3 , ALUctrl [2:0] $end
    $var wire  1 - ALUsrc $end
    $var wire 32 > DATA_WIDTH [31:0] $end
    $var wire  1 . EQ $end
    $var wire 12 0 ImmSrc [11:0] $end
    $var wire  1 + PCsrc $end
    $var wire  1 / RegWrite $end
    $var wire  3 ) funct3 [2:0] $end
    $var wire 32 # instr [31:0] $end
    $var wire  7 ( opcode [6:0] $end
   $upscope $end
   $scope module immext $end
    $var wire 32 1 ImmOp [31:0] $end
    $var wire 12 0 ImmSrc [11:0] $end
    $var wire 20 3 imm [19:0] $end
    $var wire 32 # instr [31:0] $end
    $var wire  7 ( opcode [6:0] $end
    $var wire  5 * rd [4:0] $end
   $upscope $end
   $scope module memory $end
    $var wire 32 > ADDRESS_WIDTH [31:0] $end
    $var wire 32 > DATA_WIDTH [31:0] $end
    $var wire 32 7 addr [31:0] $end
    $var wire 32 # instr [31:0] $end
   $upscope $end
   $scope module pc $end
    $var wire 32 1 ImmOp [31:0] $end
    $var wire 32 7 PC [31:0] $end
    $var wire  1 + PCsrc $end
    $var wire  1 4 clk $end
    $var wire 32 : next_PC [31:0] $end
    $var wire  1 5 rst $end
    $scope module Countermux $end
     $var wire 32 1 ImmOp [31:0] $end
     $var wire 32 7 PC [31:0] $end
     $var wire  1 + PCsrc $end
     $var wire 32 ; branch_PC [31:0] $end
     $var wire 32 < inc_PC [31:0] $end
     $var wire 32 : next_PC [31:0] $end
    $upscope $end
    $scope module PC_Reg $end
     $var wire 32 7 PC [31:0] $end
     $var wire  1 4 clk $end
     $var wire 32 : next_PC [31:0] $end
     $var wire  1 5 rst $end
     $var wire 32 7 sreg [31:0] $end
    $upscope $end
   $upscope $end
  $upscope $end
 $upscope $end
$enddefinitions $end


#0
b00000000000000000000000000000000 #
b0000000000000000 $
b0000000000000000 %
b0000000000000000 &
b00000000000000000000000000000000 '
b0000000 (
b000 )
b00000 *
0+
b000 ,
0-
0.
0/
b000000000000 0
b00000000000000000000000000000000 1
b00000000000000000000000000000000 2
b00000000000000000000 3
14
15
b00000000000000000000000000000000 6
b00000000000000000000000000000000 7
b00000000000000000000000000000000 8
b00000000000000000000000000000000 9
b00000000000000000000000000000100 :
b00000000000000000000000000000000 ;
b00000000000000000000000000000100 <
b00000000000000000000000000010000 =
b00000000000000000000000000100000 >
#1
b00010011100100110001001100010011 #
b0000000000000110 $
b0000000000011001 %
b0000000000000110 &
b0010011 (
b001 )
b00110 *
1.
b00000000000000000000001100010011 1
04
b00000000000000000000001100010011 ;
#2
14
#3
04
#4
14
#5
04
#6
14
#7
04
#8
14
05
#9
04
#10
b00000000000000001110001110010011 #
b0000000000000001 $
b0000000000000000 %
b0000000000000111 &
b110 )
b00111 *
b00000000000000000000001110010011 1
14
b00000000000000000000000000000100 7
b00000000000000000000000000001000 :
b00000000000000000000001110010111 ;
b00000000000000000000000000001000 <
#11
04
#12
b00000000000000000000000000000000 #
b0000000000000000 $
b0000000000000000 &
b0000000 (
b000 )
b00000 *
14
b00000000000000000000000000001000 7
b00000000000000000000000000001100 :
b00000000000000000000001110011011 ;
b00000000000000000000000000001100 <
#13
04
#14
14
b00000000000000000000000000001100 7
b00000000000000000000000000010000 :
b00000000000000000000001110011111 ;
b00000000000000000000000000010000 <
#15
04
#16
14
b00000000000000000000000000010000 7
b00000000000000000000000000010100 :
b00000000000000000000001110100011 ;
b00000000000000000000000000010100 <
#17
04
#18
14
b00000000000000000000000000010100 7
b00000000000000000000000000011000 :
b00000000000000000000001110100111 ;
b00000000000000000000000000011000 <
#19
04
#20
14
b00000000000000000000000000011000 7
b00000000000000000000000000011100 :
b00000000000000000000001110101011 ;
b00000000000000000000000000011100 <
#21
04
#22
14
b00000000000000000000000000011100 7
b00000000000000000000000000100000 :
b00000000000000000000001110101111 ;
b00000000000000000000000000100000 <
#23
04
#24
14
b00000000000000000000000000100000 7
b00000000000000000000000000100100 :
b00000000000000000000001110110011 ;
b00000000000000000000000000100100 <
#25
04
#26
14
b00000000000000000000000000100100 7
b00000000000000000000000000101000 :
b00000000000000000000001110110111 ;
b00000000000000000000000000101000 <
#27
04
#28
14
b00000000000000000000000000101000 7
b00000000000000000000000000101100 :
b00000000000000000000001110111011 ;
b00000000000000000000000000101100 <
#29
04
#30
14
b00000000000000000000000000101100 7
b00000000000000000000000000110000 :
b00000000000000000000001110111111 ;
b00000000000000000000000000110000 <
#31
04
#32
14
b00000000000000000000000000110000 7
b00000000000000000000000000110100 :
b00000000000000000000001111000011 ;
b00000000000000000000000000110100 <
#33
04
#34
14
b00000000000000000000000000110100 7
b00000000000000000000000000111000 :
b00000000000000000000001111000111 ;
b00000000000000000000000000111000 <
#35
04
#36
14
b00000000000000000000000000111000 7
b00000000000000000000000000111100 :
b00000000000000000000001111001011 ;
b00000000000000000000000000111100 <
#37
04
#38
14
b00000000000000000000000000111100 7
b00000000000000000000000001000000 :
b00000000000000000000001111001111 ;
b00000000000000000000000001000000 <
#39
04
#40
14
b00000000000000000000000001000000 7
b00000000000000000000000001000100 :
b00000000000000000000001111010011 ;
b00000000000000000000000001000100 <
#41
04
#42
14
b00000000000000000000000001000100 7
b00000000000000000000000001001000 :
b00000000000000000000001111010111 ;
b00000000000000000000000001001000 <
#43
04
#44
14
b00000000000000000000000001001000 7
b00000000000000000000000001001100 :
b00000000000000000000001111011011 ;
b00000000000000000000000001001100 <
#45
04
#46
14
b00000000000000000000000001001100 7
b00000000000000000000000001010000 :
b00000000000000000000001111011111 ;
b00000000000000000000000001010000 <
#47
04
#48
14
b00000000000000000000000001010000 7
b00000000000000000000000001010100 :
b00000000000000000000001111100011 ;
b00000000000000000000000001010100 <
#49
04
#50
14
b00000000000000000000000001010100 7
b00000000000000000000000001011000 :
b00000000000000000000001111100111 ;
b00000000000000000000000001011000 <
#51
04
#52
14
b00000000000000000000000001011000 7
b00000000000000000000000001011100 :
b00000000000000000000001111101011 ;
b00000000000000000000000001011100 <
#53
04
#54
14
b00000000000000000000000001011100 7
b00000000000000000000000001100000 :
b00000000000000000000001111101111 ;
b00000000000000000000000001100000 <
#55
04
#56
14
b00000000000000000000000001100000 7
b00000000000000000000000001100100 :
b00000000000000000000001111110011 ;
b00000000000000000000000001100100 <
#57
04
#58
14
b00000000000000000000000001100100 7
b00000000000000000000000001101000 :
b00000000000000000000001111110111 ;
b00000000000000000000000001101000 <
#59
04
#60
14
b00000000000000000000000001101000 7
b00000000000000000000000001101100 :
b00000000000000000000001111111011 ;
b00000000000000000000000001101100 <
#61
04
#62
14
b00000000000000000000000001101100 7
b00000000000000000000000001110000 :
b00000000000000000000001111111111 ;
b00000000000000000000000001110000 <
#63
04
#64
14
b00000000000000000000000001110000 7
b00000000000000000000000001110100 :
b00000000000000000000010000000011 ;
b00000000000000000000000001110100 <
#65
04
#66
14
b00000000000000000000000001110100 7
b00000000000000000000000001111000 :
b00000000000000000000010000000111 ;
b00000000000000000000000001111000 <
#67
04
#68
14
b00000000000000000000000001111000 7
b00000000000000000000000001111100 :
b00000000000000000000010000001011 ;
b00000000000000000000000001111100 <
#69
04
#70
14
b00000000000000000000000001111100 7
b00000000000000000000000010000000 :
b00000000000000000000010000001111 ;
b00000000000000000000000010000000 <
#71
04
#72
14
b00000000000000000000000010000000 7
b00000000000000000000000010000100 :
b00000000000000000000010000010011 ;
b00000000000000000000000010000100 <
#73
04
#74
14
b00000000000000000000000010000100 7
b00000000000000000000000010001000 :
b00000000000000000000010000010111 ;
b00000000000000000000000010001000 <
#75
04
#76
14
b00000000000000000000000010001000 7
b00000000000000000000000010001100 :
b00000000000000000000010000011011 ;
b00000000000000000000000010001100 <
#77
04
#78
14
b00000000000000000000000010001100 7
b00000000000000000000000010010000 :
b00000000000000000000010000011111 ;
b00000000000000000000000010010000 <
#79
04
#80
14
b00000000000000000000000010010000 7
b00000000000000000000000010010100 :
b00000000000000000000010000100011 ;
b00000000000000000000000010010100 <
#81
04
#82
14
b00000000000000000000000010010100 7
b00000000000000000000000010011000 :
b00000000000000000000010000100111 ;
b00000000000000000000000010011000 <
#83
04
#84
14
b00000000000000000000000010011000 7
b00000000000000000000000010011100 :
b00000000000000000000010000101011 ;
b00000000000000000000000010011100 <
#85
04
#86
14
b00000000000000000000000010011100 7
b00000000000000000000000010100000 :
b00000000000000000000010000101111 ;
b00000000000000000000000010100000 <
#87
04
#88
14
b00000000000000000000000010100000 7
b00000000000000000000000010100100 :
b00000000000000000000010000110011 ;
b00000000000000000000000010100100 <
#89
04
#90
14
b00000000000000000000000010100100 7
b00000000000000000000000010101000 :
b00000000000000000000010000110111 ;
b00000000000000000000000010101000 <
#91
04
#92
14
b00000000000000000000000010101000 7
b00000000000000000000000010101100 :
b00000000000000000000010000111011 ;
b00000000000000000000000010101100 <
#93
04
#94
14
b00000000000000000000000010101100 7
b00000000000000000000000010110000 :
b00000000000000000000010000111111 ;
b00000000000000000000000010110000 <
#95
04
#96
14
b00000000000000000000000010110000 7
b00000000000000000000000010110100 :
b00000000000000000000010001000011 ;
b00000000000000000000000010110100 <
#97
04
#98
14
b00000000000000000000000010110100 7
b00000000000000000000000010111000 :
b00000000000000000000010001000111 ;
b00000000000000000000000010111000 <
#99
04
#100
14
b00000000000000000000000010111000 7
b00000000000000000000000010111100 :
b00000000000000000000010001001011 ;
b00000000000000000000000010111100 <
#101
04
#102
14
b00000000000000000000000010111100 7
b00000000000000000000000011000000 :
b00000000000000000000010001001111 ;
b00000000000000000000000011000000 <
#103
04
#104
14
b00000000000000000000000011000000 7
b00000000000000000000000011000100 :
b00000000000000000000010001010011 ;
b00000000000000000000000011000100 <
#105
04
#106
14
b00000000000000000000000011000100 7
b00000000000000000000000011001000 :
b00000000000000000000010001010111 ;
b00000000000000000000000011001000 <
#107
04
#108
14
b00000000000000000000000011001000 7
b00000000000000000000000011001100 :
b00000000000000000000010001011011 ;
b00000000000000000000000011001100 <
#109
04
#110
14
b00000000000000000000000011001100 7
b00000000000000000000000011010000 :
b00000000000000000000010001011111 ;
b00000000000000000000000011010000 <
#111
04
#112
14
b00000000000000000000000011010000 7
b00000000000000000000000011010100 :
b00000000000000000000010001100011 ;
b00000000000000000000000011010100 <
#113
04
#114
14
b00000000000000000000000011010100 7
b00000000000000000000000011011000 :
b00000000000000000000010001100111 ;
b00000000000000000000000011011000 <
#115
04
#116
14
b00000000000000000000000011011000 7
b00000000000000000000000011011100 :
b00000000000000000000010001101011 ;
b00000000000000000000000011011100 <
#117
04
#118
14
b00000000000000000000000011011100 7
b00000000000000000000000011100000 :
b00000000000000000000010001101111 ;
b00000000000000000000000011100000 <
#119
04
#120
14
b00000000000000000000000011100000 7
b00000000000000000000000011100100 :
b00000000000000000000010001110011 ;
b00000000000000000000000011100100 <
#121
04
#122
14
b00000000000000000000000011100100 7
b00000000000000000000000011101000 :
b00000000000000000000010001110111 ;
b00000000000000000000000011101000 <
#123
04
#124
14
b00000000000000000000000011101000 7
b00000000000000000000000011101100 :
b00000000000000000000010001111011 ;
b00000000000000000000000011101100 <
#125
04
#126
14
b00000000000000000000000011101100 7
b00000000000000000000000011110000 :
b00000000000000000000010001111111 ;
b00000000000000000000000011110000 <
#127
04
#128
14
b00000000000000000000000011110000 7
b00000000000000000000000011110100 :
b00000000000000000000010010000011 ;
b00000000000000000000000011110100 <
#129
04
#130
14
b00000000000000000000000011110100 7
b00000000000000000000000011111000 :
b00000000000000000000010010000111 ;
b00000000000000000000000011111000 <
#131
04
#132
14
b00000000000000000000000011111000 7
b00000000000000000000000011111100 :
b00000000000000000000010010001011 ;
b00000000000000000000000011111100 <
#133
04
#134
14
b00000000000000000000000011111100 7
b00000000000000000000000100000000 :
b00000000000000000000010010001111 ;
b00000000000000000000000100000000 <
#135
04
#136
14
b00000000000000000000000100000000 7
b00000000000000000000000100000100 :
b00000000000000000000010010010011 ;
b00000000000000000000000100000100 <
#137
04
#138
14
b00000000000000000000000100000100 7
b00000000000000000000000100001000 :
b00000000000000000000010010010111 ;
b00000000000000000000000100001000 <
#139
04
#140
14
b00000000000000000000000100001000 7
b00000000000000000000000100001100 :
b00000000000000000000010010011011 ;
b00000000000000000000000100001100 <
#141
04
#142
14
b00000000000000000000000100001100 7
b00000000000000000000000100010000 :
b00000000000000000000010010011111 ;
b00000000000000000000000100010000 <
#143
04
#144
14
b00000000000000000000000100010000 7
b00000000000000000000000100010100 :
b00000000000000000000010010100011 ;
b00000000000000000000000100010100 <
#145
04
#146
14
b00000000000000000000000100010100 7
b00000000000000000000000100011000 :
b00000000000000000000010010100111 ;
b00000000000000000000000100011000 <
#147
04
#148
14
b00000000000000000000000100011000 7
b00000000000000000000000100011100 :
b00000000000000000000010010101011 ;
b00000000000000000000000100011100 <
#149
04
#150
14
b00000000000000000000000100011100 7
b00000000000000000000000100100000 :
b00000000000000000000010010101111 ;
b00000000000000000000000100100000 <
#151
04
#152
14
b00000000000000000000000100100000 7
b00000000000000000000000100100100 :
b00000000000000000000010010110011 ;
b00000000000000000000000100100100 <
#153
04
#154
14
b00000000000000000000000100100100 7
b00000000000000000000000100101000 :
b00000000000000000000010010110111 ;
b00000000000000000000000100101000 <
#155
04
#156
14
b00000000000000000000000100101000 7
b00000000000000000000000100101100 :
b00000000000000000000010010111011 ;
b00000000000000000000000100101100 <
#157
04
#158
14
b00000000000000000000000100101100 7
b00000000000000000000000100110000 :
b00000000000000000000010010111111 ;
b00000000000000000000000100110000 <
#159
04
#160
14
b00000000000000000000000100110000 7
b00000000000000000000000100110100 :
b00000000000000000000010011000011 ;
b00000000000000000000000100110100 <
#161
04
#162
14
b00000000000000000000000100110100 7
b00000000000000000000000100111000 :
b00000000000000000000010011000111 ;
b00000000000000000000000100111000 <
#163
04
#164
14
b00000000000000000000000100111000 7
b00000000000000000000000100111100 :
b00000000000000000000010011001011 ;
b00000000000000000000000100111100 <
#165
04
#166
14
b00000000000000000000000100111100 7
b00000000000000000000000101000000 :
b00000000000000000000010011001111 ;
b00000000000000000000000101000000 <
#167
04
#168
14
b00000000000000000000000101000000 7
b00000000000000000000000101000100 :
b00000000000000000000010011010011 ;
b00000000000000000000000101000100 <
#169
04
#170
14
b00000000000000000000000101000100 7
b00000000000000000000000101001000 :
b00000000000000000000010011010111 ;
b00000000000000000000000101001000 <
#171
04
#172
14
b00000000000000000000000101001000 7
b00000000000000000000000101001100 :
b00000000000000000000010011011011 ;
b00000000000000000000000101001100 <
#173
04
#174
14
b00000000000000000000000101001100 7
b00000000000000000000000101010000 :
b00000000000000000000010011011111 ;
b00000000000000000000000101010000 <
#175
04
#176
14
b00000000000000000000000101010000 7
b00000000000000000000000101010100 :
b00000000000000000000010011100011 ;
b00000000000000000000000101010100 <
#177
04
#178
14
b00000000000000000000000101010100 7
b00000000000000000000000101011000 :
b00000000000000000000010011100111 ;
b00000000000000000000000101011000 <
#179
04
#180
14
b00000000000000000000000101011000 7
b00000000000000000000000101011100 :
b00000000000000000000010011101011 ;
b00000000000000000000000101011100 <
#181
04
#182
14
b00000000000000000000000101011100 7
b00000000000000000000000101100000 :
b00000000000000000000010011101111 ;
b00000000000000000000000101100000 <
#183
04
#184
14
b00000000000000000000000101100000 7
b00000000000000000000000101100100 :
b00000000000000000000010011110011 ;
b00000000000000000000000101100100 <
#185
04
#186
14
b00000000000000000000000101100100 7
b00000000000000000000000101101000 :
b00000000000000000000010011110111 ;
b00000000000000000000000101101000 <
#187
04
#188
14
b00000000000000000000000101101000 7
b00000000000000000000000101101100 :
b00000000000000000000010011111011 ;
b00000000000000000000000101101100 <
#189
04
#190
14
b00000000000000000000000101101100 7
b00000000000000000000000101110000 :
b00000000000000000000010011111111 ;
b00000000000000000000000101110000 <
#191
04
#192
14
b00000000000000000000000101110000 7
b00000000000000000000000101110100 :
b00000000000000000000010100000011 ;
b00000000000000000000000101110100 <
#193
04
#194
14
b00000000000000000000000101110100 7
b00000000000000000000000101111000 :
b00000000000000000000010100000111 ;
b00000000000000000000000101111000 <
#195
04
#196
14
b00000000000000000000000101111000 7
b00000000000000000000000101111100 :
b00000000000000000000010100001011 ;
b00000000000000000000000101111100 <
#197
04
#198
14
b00000000000000000000000101111100 7
b00000000000000000000000110000000 :
b00000000000000000000010100001111 ;
b00000000000000000000000110000000 <
#199
04
#200
14
b00000000000000000000000110000000 7
b00000000000000000000000110000100 :
b00000000000000000000010100010011 ;
b00000000000000000000000110000100 <
#201
04
#202
14
b00000000000000000000000110000100 7
b00000000000000000000000110001000 :
b00000000000000000000010100010111 ;
b00000000000000000000000110001000 <
#203
04
#204
14
b00000000000000000000000110001000 7
b00000000000000000000000110001100 :
b00000000000000000000010100011011 ;
b00000000000000000000000110001100 <
#205
04
#206
14
b00000000000000000000000110001100 7
b00000000000000000000000110010000 :
b00000000000000000000010100011111 ;
b00000000000000000000000110010000 <
#207
04
#208
14
b00000000000000000000000110010000 7
b00000000000000000000000110010100 :
b00000000000000000000010100100011 ;
b00000000000000000000000110010100 <
#209
04
#210
14
b00000000000000000000000110010100 7
b00000000000000000000000110011000 :
b00000000000000000000010100100111 ;
b00000000000000000000000110011000 <
#211
04
#212
14
b00000000000000000000000110011000 7
b00000000000000000000000110011100 :
b00000000000000000000010100101011 ;
b00000000000000000000000110011100 <
#213
04
#214
14
b00000000000000000000000110011100 7
b00000000000000000000000110100000 :
b00000000000000000000010100101111 ;
b00000000000000000000000110100000 <
#215
04
#216
14
b00000000000000000000000110100000 7
b00000000000000000000000110100100 :
b00000000000000000000010100110011 ;
b00000000000000000000000110100100 <
#217
04
#218
14
b00000000000000000000000110100100 7
b00000000000000000000000110101000 :
b00000000000000000000010100110111 ;
b00000000000000000000000110101000 <
#219
04
#220
14
b00000000000000000000000110101000 7
b00000000000000000000000110101100 :
b00000000000000000000010100111011 ;
b00000000000000000000000110101100 <
#221
04
#222
14
b00000000000000000000000110101100 7
b00000000000000000000000110110000 :
b00000000000000000000010100111111 ;
b00000000000000000000000110110000 <
#223
04
#224
14
b00000000000000000000000110110000 7
b00000000000000000000000110110100 :
b00000000000000000000010101000011 ;
b00000000000000000000000110110100 <
#225
04
#226
14
b00000000000000000000000110110100 7
b00000000000000000000000110111000 :
b00000000000000000000010101000111 ;
b00000000000000000000000110111000 <
#227
04
#228
14
b00000000000000000000000110111000 7
b00000000000000000000000110111100 :
b00000000000000000000010101001011 ;
b00000000000000000000000110111100 <
#229
04
#230
14
b00000000000000000000000110111100 7
b00000000000000000000000111000000 :
b00000000000000000000010101001111 ;
b00000000000000000000000111000000 <
#231
04
#232
14
b00000000000000000000000111000000 7
b00000000000000000000000111000100 :
b00000000000000000000010101010011 ;
b00000000000000000000000111000100 <
#233
04
#234
14
b00000000000000000000000111000100 7
b00000000000000000000000111001000 :
b00000000000000000000010101010111 ;
b00000000000000000000000111001000 <
#235
04
#236
14
b00000000000000000000000111001000 7
b00000000000000000000000111001100 :
b00000000000000000000010101011011 ;
b00000000000000000000000111001100 <
#237
04
#238
14
b00000000000000000000000111001100 7
b00000000000000000000000111010000 :
b00000000000000000000010101011111 ;
b00000000000000000000000111010000 <
#239
04
#240
14
b00000000000000000000000111010000 7
b00000000000000000000000111010100 :
b00000000000000000000010101100011 ;
b00000000000000000000000111010100 <
#241
04
#242
14
b00000000000000000000000111010100 7
b00000000000000000000000111011000 :
b00000000000000000000010101100111 ;
b00000000000000000000000111011000 <
#243
04
#244
14
b00000000000000000000000111011000 7
b00000000000000000000000111011100 :
b00000000000000000000010101101011 ;
b00000000000000000000000111011100 <
#245
04
#246
14
b00000000000000000000000111011100 7
b00000000000000000000000111100000 :
b00000000000000000000010101101111 ;
b00000000000000000000000111100000 <
#247
04
#248
14
b00000000000000000000000111100000 7
b00000000000000000000000111100100 :
b00000000000000000000010101110011 ;
b00000000000000000000000111100100 <
#249
04
#250
14
b00000000000000000000000111100100 7
b00000000000000000000000111101000 :
b00000000000000000000010101110111 ;
b00000000000000000000000111101000 <
#251
04
#252
14
b00000000000000000000000111101000 7
b00000000000000000000000111101100 :
b00000000000000000000010101111011 ;
b00000000000000000000000111101100 <
#253
04
#254
14
b00000000000000000000000111101100 7
b00000000000000000000000111110000 :
b00000000000000000000010101111111 ;
b00000000000000000000000111110000 <
#255
04
